Metadata-Version: 1.2
Name: python-bootstrapper
Version: 0.0.0a0
Summary:  Provides a simple starter module for creating new Python projects.
Home-page: https://github.com/monokrome/python-bootstrapper
Author: Bailey "monokrome" Stoner
Author-email: monokrome@monokro.me
Maintainer: Bailey "monokrome" Stoner
Maintainer-email: monokrome@monokro.me
License: BSD 3-Clause License
Platform: UNKNOWN
